tickertock/__init__.py
tickertock/clockify.py
tickertock/config.py
tickertock/tickertock.py
tickertock/ui.py
tickertock/utils.py
tickertock/scripts/__init__.py
tickertock/scripts/tickertock.py
tickertock/skel/__init__.py
tickertock/skel/config.toml.j2
tickertock/skel/projects.toml
tickertock/skel/streamdeck_ui.json.j2
tickertock/skel/assets/paused.png
tickertock/skel/assets/paused.svg
tickertock-0.1.3.dist-info/licenses/LICENSE.txt
tickertock-0.1.3.dist-info/METADATA
tickertock-0.1.3.dist-info/WHEEL
tickertock-0.1.3.dist-info/entry_points.txt
tickertock-0.1.3.dist-info/top_level.txt
tickertock-0.1.3.dist-info/RECORD
