Metadata-Version: 2.4
Name: tickertock
Version: 0.1.3
Summary: Streamdeck as a timetracker
License: MIT License
Keywords: timetracking,clockify
Classifier: Programming Language :: Python :: 3
Requires-Python: >=3.7
License-File: LICENSE.txt
Requires-Dist: streamdeck_ui>2.0
Requires-Dist: pycairo
Requires-Dist: jinja2
Requires-Dist: filetype
Requires-Dist: toml
Requires-Dist: PySide6
Requires-Dist: clockify
Requires-Dist: click
Requires-Dist: xdg
Dynamic: license-file
